{
  "wrong": [
    {
      "id": 1,
      "question": "1+1=?",
      "answer": "2",
      "user_answer": "0",
      "elapsed_seconds": 0.865263,
      "reaction_time_limit_seconds": 1.0,
      "is_timeout": false
    },
    {
      "id": 2,
      "question": "2+2=?",
      "answer": "4",
      "user_answer": "0",
      "elapsed_seconds": 0.991977,
      "reaction_time_limit_seconds": 1.0,
      "is_timeout": false
    },
    {
      "id": 3,
      "question": "3+3=?",
      "answer": "6",
      "user_answer": "0",
      "elapsed_seconds": 2.585761,
      "reaction_time_limit_seconds": 1.0,
      "is_timeout": true
    },
    {
      "id": 4,
      "question": [
        "数组测试,",
        "诶嘿."
      ],
      "answer": "enen",
      "user_answer": "0",
      "elapsed_seconds": 0.213117,
      "reaction_time_limit_seconds": 1.0,
      "is_timeout": false
    },
    {
      "id": 5,
      "question": [
        "嘿嘿嘿哈, ",
        "嗯嗯"
      ],
      "answer": [
        "hello, ",
        "很"
      ],
      "user_answer": "0",
      "elapsed_seconds": 0.921123,
      "reaction_time_limit_seconds": 1.0,
      "is_timeout": false
    }
  ],
  "time out": []
}